Workbook
Name MoedaBase: Config!$B$4
Name TaxaCambioTbl: Config!$A$16:$D$25
Name ListaMoedas: Config!$A$16:$A$25
Name CatDespesa: Config!$F$16:$F$25
Name FormaPagto: Config!$H$16:$H$21
Name Prioridade: Config!$J$16:$J$18
Name StatusCompra: Config!$K$16:$K$17
Name StatusItem: Config!$L$16:$L$17
Name StatusItinerario: Config!$M$16:$M$18
Name CatCompras: Config!$N$16:$N$22
Name OrcCategoria: Orcamento!$A$4:$A$13
Name OrcValorBase: Orcamento!$E$4:$E$13
Name OrcTotal: Orcamento!$E$14
Name DespData: Despesas!$A$4:$A$38
Name DespCategoria: Despesas!$C$4:$C$38
Name DespValorBase: Despesas!$H$4:$H$38
Name DespTotal: Despesas!$H$39
Name ComprasTotal: Compras!$G$25
Name HistViagem: Historico!$A$4:$A$33
Name HistGasto: Historico!$I$4:$I$33
Name HistOrcamento: Historico!$H$4:$H$33

Sheet Painel
A1: PAINEL FINANCEIRO DA VIAGEM
A3: Viagem: | B3: =Config!B5 | F3: COMO USAR
A4: Destino: | B4: =Config!B6 | F4: Células AZUIS = você edita. Células pretas = fórmulas (não mexa).
A5: Período: | B5: =TEXT(Config!B7,"dd/mm/yyyy")&" a "&TEXT(Config!B8,"dd/mm/yyyy")&" ("&Config!B9&" dias)" | F5: Ajuste tudo na aba Config primeiro (moeda, datas, câmbio).
A6: Moeda Base / Viajantes: | B6: =Config!B4&" / "&Config!B10&" pessoa(s)" | F6: Ao abrir no Excel/Google Sheets os valores recalculam sozinhos.
F7: Fim da viagem: rode a macro "Arquivar Viagem" (veja instruções em anexo) para salvar o resumo na aba Historico e limpar tudo para a próxima viagem.
A8: ORÇAMENTO TOTAL | B8: TOTAL GASTO | C8: SALDO DISPONÍVEL | D8: % ORÇAMENTO USADO
A9: =OrcTotal | B9: =DespTotal | C9: =OrcTotal-DespTotal | D9: =IFERROR(DespTotal/OrcTotal,0)
A11: Gasto médio por dia: | B11: =IFERROR(DespTotal/Config!B9,0)
A12: Gasto médio por pessoa/dia: | B12: =IFERROR(DespTotal/Config!B9/Config!B10,0)
A14: RESUMO POR CATEGORIA | G14: GASTO ACUMULADO POR DIA
A15: Categoria | B15: Orçamento | C15: Gasto Real | D15: Saldo | E15: % Usado | G15: Data | H15: Acumulado
A16: =Orcamento!A4 | B16: =Orcamento!E4 | C16: =SUMIFS(DespValorBase,DespCategoria,A16) | D16: =B16-C16 | E16: =IFERROR(C16/B16,0) | G16: =Config!B7 | H16: =IF(G16="","",SUMIFS(DespValorBase,DespData,"<="&G16))
A17: =Orcamento!A5 | B17: =Orcamento!E5 | C17: =SUMIFS(DespValorBase,DespCategoria,A17) | D17: =B17-C17 | E17: =IFERROR(C17/B17,0) | G17: =IF(G16="","",IF(G16>=Config!$B$8,"",G16+1)) | H17: =IF(G17="","",SUMIFS(DespValorBase,DespData,"<="&G17))
A18: =Orcamento!A6 | B18: =Orcamento!E6 | C18: =SUMIFS(DespValorBase,DespCategoria,A18) | D18: =B18-C18 | E18: =IFERROR(C18/B18,0) | G18: =IF(G17="","",IF(G17>=Config!$B$8,"",G17+1)) | H18: =IF(G18="","",SUMIFS(DespValorBase,DespData,"<="&G18))
A19: =Orcamento!A7 | B19: =Orcamento!E7 | C19: =SUMIFS(DespValorBase,DespCategoria,A19) | D19: =B19-C19 | E19: =IFERROR(C19/B19,0) | G19: =IF(G18="","",IF(G18>=Config!$B$8,"",G18+1)) | H19: =IF(G19="","",SUMIFS(DespValorBase,DespData,"<="&G19))
A20: =Orcamento!A8 | B20: =Orcamento!E8 | C20: =SUMIFS(DespValorBase,DespCategoria,A20) | D20: =B20-C20 | E20: =IFERROR(C20/B20,0) | G20: =IF(G19="","",IF(G19>=Config!$B$8,"",G19+1)) | H20: =IF(G20="","",SUMIFS(DespValorBase,DespData,"<="&G20))
A21: =Orcamento!A9 | B21: =Orcamento!E9 | C21: =SUMIFS(DespValorBase,DespCategoria,A21) | D21: =B21-C21 | E21: =IFERROR(C21/B21,0) | G21: =IF(G20="","",IF(G20>=Config!$B$8,"",G20+1)) | H21: =IF(G21="","",SUMIFS(DespValorBase,DespData,"<="&G21))
A22: =Orcamento!A10 | B22: =Orcamento!E10 | C22: =SUMIFS(DespValorBase,DespCategoria,A22) | D22: =B22-C22 | E22: =IFERROR(C22/B22,0) | G22: =IF(G21="","",IF(G21>=Config!$B$8,"",G21+1)) | H22: =IF(G22="","",SUMIFS(DespValorBase,DespData,"<="&G22))
A23: =Orcamento!A11 | B23: =Orcamento!E11 | C23: =SUMIFS(DespValorBase,DespCategoria,A23) | D23: =B23-C23 | E23: =IFERROR(C23/B23,0) | G23: =IF(G22="","",IF(G22>=Config!$B$8,"",G22+1)) | H23: =IF(G23="","",SUMIFS(DespValorBase,DespData,"<="&G23))
A24: =Orcamento!A12 | B24: =Orcamento!E12 | C24: =SUMIFS(DespValorBase,DespCategoria,A24) | D24: =B24-C24 | E24: =IFERROR(C24/B24,0) | G24: =IF(G23="","",IF(G23>=Config!$B$8,"",G23+1)) | H24: =IF(G24="","",SUMIFS(DespValorBase,DespData,"<="&G24))
A25: =Orcamento!A13 | B25: =Orcamento!E13 | C25: =SUMIFS(DespValorBase,DespCategoria,A25) | D25: =B25-C25 | E25: =IFERROR(C25/B25,0) | G25: =IF(G24="","",IF(G24>=Config!$B$8,"",G24+1)) | H25: =IF(G25="","",SUMIFS(DespValorBase,DespData,"<="&G25))
G26: =IF(G25="","",IF(G25>=Config!$B$8,"",G25+1)) | H26: =IF(G26="","",SUMIFS(DespValorBase,DespData,"<="&G26))
G27: =IF(G26="","",IF(G26>=Config!$B$8,"",G26+1)) | H27: =IF(G27="","",SUMIFS(DespValorBase,DespData,"<="&G27))
G28: =IF(G27="","",IF(G27>=Config!$B$8,"",G27+1)) | H28: =IF(G28="","",SUMIFS(DespValorBase,DespData,"<="&G28))
G29: =IF(G28="","",IF(G28>=Config!$B$8,"",G28+1)) | H29: =IF(G29="","",SUMIFS(DespValorBase,DespData,"<="&G29))
G30: =IF(G29="","",IF(G29>=Config!$B$8,"",G29+1)) | H30: =IF(G30="","",SUMIFS(DespValorBase,DespData,"<="&G30))

Sheet Config
A1: CONFIGURAÇÕES DA VIAGEM
A2: Preencha as células em azul. Todas as outras planilhas usam estes dados automaticamente.
A4: Moeda Base (moeda dos seus totais): | B4: BRL
A5: Nome da Viagem: | B5: Viagem para Lisboa e Porto
A6: Destino: | B6: Lisboa e Porto, Portugal
A7: Data de Início: | B7: 46275
A8: Data de Fim: | B8: 46285
A9: Número de Dias: | B9: =B8-B7+1
A10: Número de Viajantes: | B10: 2
A11: Moeda Local do Destino: | B11: EUR
A13: TABELA DE CÂMBIO
A14: Exemplo — atualize as taxas com a cotação do dia da sua viagem (ex.: Google "câmbio USD BRL").
A15: Código | B15: Nome da Moeda | C15: Taxa p/ Moeda Base | D15: Atualizado em | F15: Categorias de Despesa | H15: Formas de Pagamento | J15: Prioridade | K15: Comprado? | L15: Status Item | M15: Status Itinerário | N15: Categorias de Compras
A16: BRL | B16: Real Brasileiro | C16: 1 | D16: Exemplo (03/08/2026) | F16: Hospedagem | H16: Cartão de Crédito | J16: Alta | K16: Sim | L16: Pendente | M16: Confirmado | N16: Roupas e Calçados
A17: USD | B17: Dólar Americano | C17: 5.4 | D17: Exemplo (03/08/2026) | F17: Passagens Aéreas | H17: Cartão de Débito | J17: Média | K17: Não | L17: Feito | M17: Pendente | N17: Eletrônicos
A18: EUR | B18: Euro | C18: 5.9 | D18: Exemplo (03/08/2026) | F18: Transporte Local | H18: Dinheiro | J18: Baixa | M18: Cancelado | N18: Presentes/Souvenirs
A19: GBP | B19: Libra Esterlina | C19: 6.9 | D19: Exemplo (03/08/2026) | F19: Alimentação | H19: Pix | N19: Cosméticos/Perfumes
A20: ARS | B20: Peso Argentino | C20: 0.0055 | D20: Exemplo (03/08/2026) | F20: Passeios e Atividades | H20: Transferência Bancária | N20: Alimentos e Bebidas
A21: JPY | B21: Iene Japonês | C21: 0.036 | D21: Exemplo (03/08/2026) | F21: Compras e Presentes | H21: Voucher/Milhas | N21: Artigos de Casa
A22: CLP | B22: Peso Chileno | C22: 0.0056 | D22: Exemplo (03/08/2026) | F22: Seguro Viagem | N22: Outros
A23: MXN | B23: Peso Mexicano | C23: 0.28 | D23: Exemplo (03/08/2026) | F23: Documentos e Vistos
A24: COP | B24: Peso Colombiano | C24: 0.0013 | D24: Exemplo (03/08/2026) | F24: Comunicação (Chip/Internet)
A25: UYU | B25: Peso Uruguaio | C25: 0.14 | D25: Exemplo (03/08/2026) | F25: Emergência/Imprevistos

Sheet Planejamento
A1: PLANEJAMENTO DA VIAGEM — ITINERÁRIO
A2: Linhas 4-14 são EXEMPLOS (roteiro Lisboa/Porto). Ajuste datas, atividades e custos para o seu roteiro.
A3: Data | B3: Dia da Semana | C3: Horário | D3: Atividade / Local | E3: Categoria | F3: Custo Estimado (Moeda Local) | G3: Moeda | H3: Taxa de Câmbio | I3: Custo Estimado (Moeda Base) | J3: Status | K3: Notas
A4: 46275 | B4: =IF(A4="","",CHOOSE(WEEKDAY(A4,2),"Segunda","Terça","Quarta","Quinta","Sexta","Sábado","Domingo")) | C4: 15:00 | D4: Chegada e check-in - Lisboa | E4: Hospedagem | F4: 0 | G4: EUR | H4: =IF(G4="","",IFERROR(INDEX(TaxaCambioTbl,MATCH(G4,ListaMoedas,0),3),1)) | I4: =IF(F4="","",F4*H4) | J4: Confirmado
A5: 46276 | B5: =IF(A5="","",CHOOSE(WEEKDAY(A5,2),"Segunda","Terça","Quarta","Quinta","Sexta","Sábado","Domingo")) | C5: 09:00 | D5: City tour a pé - Alfama | E5: Passeios e Atividades | F5: 0 | G5: EUR | H5: =IF(G5="","",IFERROR(INDEX(TaxaCambioTbl,MATCH(G5,ListaMoedas,0),3),1)) | I5: =IF(F5="","",F5*H5) | J5: Confirmado
A6: 46277 | B6: =IF(A6="","",CHOOSE(WEEKDAY(A6,2),"Segunda","Terça","Quarta","Quinta","Sexta","Sábado","Domingo")) | C6: 08:00 | D6: Excursão a Sintra | E6: Passeios e Atividades | F6: 65 | G6: EUR | H6: =IF(G6="","",IFERROR(INDEX(TaxaCambioTbl,MATCH(G6,ListaMoedas,0),3),1)) | I6: =IF(F6="","",F6*H6) | J6: Confirmado
A7: 46278 | B7: =IF(A7="","",CHOOSE(WEEKDAY(A7,2),"Segunda","Terça","Quarta","Quinta","Sexta","Sábado","Domingo")) | C7: 10:00 | D7: Torre de Belém e Mosteiro | E7: Passeios e Atividades | F7: 20 | G7: EUR | H7: =IF(G7="","",IFERROR(INDEX(TaxaCambioTbl,MATCH(G7,ListaMoedas,0),3),1)) | I7: =IF(F7="","",F7*H7) | J7: Pendente
A8: 46279 | B8: =IF(A8="","",CHOOSE(WEEKDAY(A8,2),"Segunda","Terça","Quarta","Quinta","Sexta","Sábado","Domingo")) | C8: 07:30 | D8: Trem para o Porto | E8: Transporte Local | F8: 35 | G8: EUR | H8: =IF(G8="","",IFERROR(INDEX(TaxaCambioTbl,MATCH(G8,ListaMoedas,0),3),1)) | I8: =IF(F8="","",F8*H8) | J8: Confirmado
A9: 46280 | B9: =IF(A9="","",CHOOSE(WEEKDAY(A9,2),"Segunda","Terça","Quarta","Quinta","Sexta","Sábado","Domingo")) | C9: 09:00 | D9: Livraria Lello e Ribeira | E9: Passeios e Atividades | F9: 15 | G9: EUR | H9: =IF(G9="","",IFERROR(INDEX(TaxaCambioTbl,MATCH(G9,ListaMoedas,0),3),1)) | I9: =IF(F9="","",F9*H9) | J9: Pendente
A10: 46281 | B10: =IF(A10="","",CHOOSE(WEEKDAY(A10,2),"Segunda","Terça","Quarta","Quinta","Sexta","Sábado","Domingo")) | C10: 14:00 | D10: Passeio de barco no Douro | E10: Passeios e Atividades | F10: 45 | G10: EUR | H10: =IF(G10="","",IFERROR(INDEX(TaxaCambioTbl,MATCH(G10,ListaMoedas,0),3),1)) | I10: =IF(F10="","",F10*H10) | J10: Pendente
A11: 46282 | B11: =IF(A11="","",CHOOSE(WEEKDAY(A11,2),"Segunda","Terça","Quarta","Quinta","Sexta","Sábado","Domingo")) | C11: 11:00 | D11: Caves de Vinho do Porto | E11: Passeios e Atividades | F11: 25 | G11: EUR | H11: =IF(G11="","",IFERROR(INDEX(TaxaCambioTbl,MATCH(G11,ListaMoedas,0),3),1)) | I11: =IF(F11="","",F11*H11) | J11: Pendente
A12: 46283 | B12: =IF(A12="","",CHOOSE(WEEKDAY(A12,2),"Segunda","Terça","Quarta","Quinta","Sexta","Sábado","Domingo")) | C12: 07:30 | D12: Trem de volta a Lisboa | E12: Transporte Local | F12: 35 | G12: EUR | H12: =IF(G12="","",IFERROR(INDEX(TaxaCambioTbl,MATCH(G12,ListaMoedas,0),3),1)) | I12: =IF(F12="","",F12*H12) | J12: Confirmado
A13: 46284 | B13: =IF(A13="","",CHOOSE(WEEKDAY(A13,2),"Segunda","Terça","Quarta","Quinta","Sexta","Sábado","Domingo")) | C13: 10:00 | D13: Dia livre / compras | E13: Compras e Presentes | F13: 0 | G13: EUR | H13: =IF(G13="","",IFERROR(INDEX(TaxaCambioTbl,MATCH(G13,ListaMoedas,0),3),1)) | I13: =IF(F13="","",F13*H13) | J13: Pendente
A14: 46285 | B14: =IF(A14="","",CHOOSE(WEEKDAY(A14,2),"Segunda","Terça","Quarta","Quinta","Sexta","Sábado","Domingo")) | C14: 12:00 | D14: Check-out e aeroporto | E14: Transporte Local | F14: 25 | G14: EUR | H14: =IF(G14="","",IFERROR(INDEX(TaxaCambioTbl,MATCH(G14,ListaMoedas,0),3),1)) | I14: =IF(F14="","",F14*H14) | J14: Confirmado
B15: =IF(A15="","",CHOOSE(WEEKDAY(A15,2),"Segunda","Terça","Quarta","Quinta","Sexta","Sábado","Domingo")) | H15: =IF(G15="","",IFERROR(INDEX(TaxaCambioTbl,MATCH(G15,ListaMoedas,0),3),1)) | I15: =IF(F15="","",F15*H15)
B16: =IF(A16="","",CHOOSE(WEEKDAY(A16,2),"Segunda","Terça","Quarta","Quinta","Sexta","Sábado","Domingo")) | H16: =IF(G16="","",IFERROR(INDEX(TaxaCambioTbl,MATCH(G16,ListaMoedas,0),3),1)) | I16: =IF(F16="","",F16*H16)
B17: =IF(A17="","",CHOOSE(WEEKDAY(A17,2),"Segunda","Terça","Quarta","Quinta","Sexta","Sábado","Domingo")) | H17: =IF(G17="","",IFERROR(INDEX(TaxaCambioTbl,MATCH(G17,ListaMoedas,0),3),1)) | I17: =IF(F17="","",F17*H17)
B18: =IF(A18="","",CHOOSE(WEEKDAY(A18,2),"Segunda","Terça","Quarta","Quinta","Sexta","Sábado","Domingo")) | H18: =IF(G18="","",IFERROR(INDEX(TaxaCambioTbl,MATCH(G18,ListaMoedas,0),3),1)) | I18: =IF(F18="","",F18*H18)
B19: =IF(A19="","",CHOOSE(WEEKDAY(A19,2),"Segunda","Terça","Quarta","Quinta","Sexta","Sábado","Domingo")) | H19: =IF(G19="","",IFERROR(INDEX(TaxaCambioTbl,MATCH(G19,ListaMoedas,0),3),1)) | I19: =IF(F19="","",F19*H19)
B20: =IF(A20="","",CHOOSE(WEEKDAY(A20,2),"Segunda","Terça","Quarta","Quinta","Sexta","Sábado","Domingo")) | H20: =IF(G20="","",IFERROR(INDEX(TaxaCambioTbl,MATCH(G20,ListaMoedas,0),3),1)) | I20: =IF(F20="","",F20*H20)
B21: =IF(A21="","",CHOOSE(WEEKDAY(A21,2),"Segunda","Terça","Quarta","Quinta","Sexta","Sábado","Domingo")) | H21: =IF(G21="","",IFERROR(INDEX(TaxaCambioTbl,MATCH(G21,ListaMoedas,0),3),1)) | I21: =IF(F21="","",F21*H21)
B22: =IF(A22="","",CHOOSE(WEEKDAY(A22,2),"Segunda","Terça","Quarta","Quinta","Sexta","Sábado","Domingo")) | H22: =IF(G22="","",IFERROR(INDEX(TaxaCambioTbl,MATCH(G22,ListaMoedas,0),3),1)) | I22: =IF(F22="","",F22*H22)
B23: =IF(A23="","",CHOOSE(WEEKDAY(A23,2),"Segunda","Terça","Quarta","Quinta","Sexta","Sábado","Domingo")) | H23: =IF(G23="","",IFERROR(INDEX(TaxaCambioTbl,MATCH(G23,ListaMoedas,0),3),1)) | I23: =IF(F23="","",F23*H23)
B24: =IF(A24="","",CHOOSE(WEEKDAY(A24,2),"Segunda","Terça","Quarta","Quinta","Sexta","Sábado","Domingo")) | H24: =IF(G24="","",IFERROR(INDEX(TaxaCambioTbl,MATCH(G24,ListaMoedas,0),3),1)) | I24: =IF(F24="","",F24*H24)
B25: =IF(A25="","",CHOOSE(WEEKDAY(A25,2),"Segunda","Terça","Quarta","Quinta","Sexta","Sábado","Domingo")) | H25: =IF(G25="","",IFERROR(INDEX(TaxaCambioTbl,MATCH(G25,ListaMoedas,0),3),1)) | I25: =IF(F25="","",F25*H25)
B26: =IF(A26="","",CHOOSE(WEEKDAY(A26,2),"Segunda","Terça","Quarta","Quinta","Sexta","Sábado","Domingo")) | H26: =IF(G26="","",IFERROR(INDEX(TaxaCambioTbl,MATCH(G26,ListaMoedas,0),3),1)) | I26: =IF(F26="","",F26*H26)
A29: CHECKLIST PRÉ-VIAGEM
A30: Item | B30: Categoria | C30: Prioridade | D30: Status
A31: Passaporte válido (6+ meses) | B31: Documentos | C31: Alta | D31: Feito
A32: Seguro viagem contratado | B32: Financeiro | C32: Alta | D32: Feito
A33: Cópias digitais dos documentos | B33: Documentos | C33: Média | D33: Pendente
A34: Câmbio de moeda / cartão internacional | B34: Financeiro | C34: Alta | D34: Pendente
A35: Notificar banco sobre a viagem | B35: Financeiro | C35: Média | D35: Pendente
A36: Reserva de hospedagem confirmada | B36: Reservas | C36: Alta | D36: Feito
A37: Passagens aéreas confirmadas | B37: Reservas | C37: Alta | D37: Feito
A38: e-SIM / chip internacional | B38: Eletrônicos | C38: Média | D38: Pendente
A39: Adaptador de tomada | B39: Eletrônicos | C39: Baixa | D39: Pendente
A40: Remédios e receitas necessárias | B40: Saúde | C40: Alta | D40: Pendente
A41: Vacinas em dia (se exigido) | B41: Saúde | C41: Média | D41: Feito
... A43: Transporte para o aeroporto agendado | B43: Reservas | C43: Média | D43: Pendente

Sheet Orcamento
A1: PREVISÃO DE GASTOS (ORÇAMENTO)
A2: Defina o orçamento previsto por categoria. A moeda pode ser diferente para cada linha — a conversão é automática.
A3: Categoria | B3: Moeda | C3: Valor Previsto (Moeda Local) | D3: Taxa de Câmbio | E3: Valor Previsto (Moeda Base) | F3: % do Orçamento Total | G3: Observações
A4: Hospedagem | B4: EUR | C4: 900 | D4: =IFERROR(INDEX(TaxaCambioTbl,MATCH(B4,ListaMoedas,0),3),1) | E4: =C4*D4 | F4: =E4/$E$14 | G4: 10 noites, apto compartilhado
A5: Passagens Aéreas | B5: BRL | C5: 3800 | D5: =IFERROR(INDEX(TaxaCambioTbl,MATCH(B5,ListaMoedas,0),3),1) | E5: =C5*D5 | F5: =E5/$E$14 | G5: Já cotado - ida e volta
A6: Transporte Local | B6: EUR | C6: 150 | D6: =IFERROR(INDEX(TaxaCambioTbl,MATCH(B6,ListaMoedas,0),3),1) | E6: =C6*D6 | F6: =E6/$E$14 | G6: Metrô, trem Lisboa-Porto
A7: Alimentação | B7: EUR | C7: 600 | D7: =IFERROR(INDEX(TaxaCambioTbl,MATCH(B7,ListaMoedas,0),3),1) | E7: =C7*D7 | F7: =E7/$E$14 | G7: Restaurantes e mercado
A8: Passeios e Atividades | B8: EUR | C8: 350 | D8: =IFERROR(INDEX(TaxaCambioTbl,MATCH(B8,ListaMoedas,0),3),1) | E8: =C8*D8 | F8: =E8/$E$14 | G8: Tours, museus, Sintra
A9: Compras e Presentes | B9: EUR | C9: 300 | D9: =IFERROR(INDEX(TaxaCambioTbl,MATCH(B9,ListaMoedas,0),3),1) | E9: =C9*D9 | F9: =E9/$E$14 | G9: Ver aba Compras
A10: Seguro Viagem | B10: BRL | C10: 250 | D10: =IFERROR(INDEX(TaxaCambioTbl,MATCH(B10,ListaMoedas,0),3),1) | E10: =C10*D10 | F10: =E10/$E$14 | G10: 10 dias, cobertura Europa
A11: Documentos e Vistos | B11: BRL | C11: 0 | D11: =IFERROR(INDEX(TaxaCambioTbl,MATCH(B11,ListaMoedas,0),3),1) | E11: =C11*D11 | F11: =E11/$E$14 | G11: Não exigido p/ brasileiros
A12: Comunicação (Chip/Internet) | B12: EUR | C12: 40 | D12: =IFERROR(INDEX(TaxaCambioTbl,MATCH(B12,ListaMoedas,0),3),1) | E12: =C12*D12 | F12: =E12/$E$14 | G12: e-SIM 10 dias
A13: Emergência/Imprevistos | B13: EUR | C13: 200 | D13: =IFERROR(INDEX(TaxaCambioTbl,MATCH(B13,ListaMoedas,0),3),1) | E13: =C13*D13 | F13: =E13/$E$14 | G13: Reserva de segurança
A14: TOTAL | E14: =SUM(E4:E13) | F14: =SUM(F4:F13)

Sheet Despesas
A1: REGISTRO DE DESPESAS (GASTOS REAIS)
A2: Linhas 4-8 são EXEMPLOS. Substitua pelos seus gastos reais. Preencha Data, Descrição, Categoria, Forma de Pagamento, Moeda e Valor — o resto é calculado.
A3: Data | B3: Descrição | C3: Categoria | D3: Forma de Pagamento | E3: Moeda | F3: Valor (Moeda Local) | G3: Taxa de Câmbio | H3: Valor (Moeda Base) | I3: Pago por | J3: Notas
A4: 46275 | B4: Check-in hotel Lisboa | C4: Hospedagem | D4: Cartão de Crédito | E4: EUR | F4: 420 | G4: =IF(E4="","",IFERROR(INDEX(TaxaCambioTbl,MATCH(E4,ListaMoedas,0),3),1)) | H4: =IF(F4="","",F4*G4) | I4: Ana
A5: 46275 | B5: Jantar de chegada | C5: Alimentação | D5: Dinheiro | E5: EUR | F5: 38.5 | G5: =IF(E5="","",IFERROR(INDEX(TaxaCambioTbl,MATCH(E5,ListaMoedas,0),3),1)) | H5: =IF(F5="","",F5*G5) | I5: Carlos
A6: 46276 | B6: Passe metrô 3 dias | C6: Transporte Local | D6: Pix | E6: EUR | F6: 18 | G6: =IF(E6="","",IFERROR(INDEX(TaxaCambioTbl,MATCH(E6,ListaMoedas,0),3),1)) | H6: =IF(F6="","",F6*G6) | I6: Ana
A7: 46277 | B7: Tour Sintra dia inteiro | C7: Passeios e Atividades | D7: Cartão de Crédito | E7: EUR | F7: 65 | G7: =IF(E7="","",IFERROR(INDEX(TaxaCambioTbl,MATCH(E7,ListaMoedas,0),3),1)) | H7: =IF(F7="","",F7*G7) | I7: Carlos
A8: 46278 | B8: e-SIM 10 dias dados | C8: Comunicação (Chip/Internet) | D8: Cartão de Débito | E8: EUR | F8: 22 | G8: =IF(E8="","",IFERROR(INDEX(TaxaCambioTbl,MATCH(E8,ListaMoedas,0),3),1)) | H8: =IF(F8="","",F8*G8) | I8: Ana
G9: =IF(E9="","",IFERROR(INDEX(TaxaCambioTbl,MATCH(E9,ListaMoedas,0),3),1)) | H9: =IF(F9="","",F9*G9)
G10: =IF(E10="","",IFERROR(INDEX(TaxaCambioTbl,MATCH(E10,ListaMoedas,0),3),1)) | H10: =IF(F10="","",F10*G10)
G11: =IF(E11="","",IFERROR(INDEX(TaxaCambioTbl,MATCH(E11,ListaMoedas,0),3),1)) | H11: =IF(F11="","",F11*G11)
G12: =IF(E12="","",IFERROR(INDEX(TaxaCambioTbl,MATCH(E12,ListaMoedas,0),3),1)) | H12: =IF(F12="","",F12*G12)
G13: =IF(E13="","",IFERROR(INDEX(TaxaCambioTbl,MATCH(E13,ListaMoedas,0),3),1)) | H13: =IF(F13="","",F13*G13)
G14: =IF(E14="","",IFERROR(INDEX(TaxaCambioTbl,MATCH(E14,ListaMoedas,0),3),1)) | H14: =IF(F14="","",F14*G14)
G15: =IF(E15="","",IFERROR(INDEX(TaxaCambioTbl,MATCH(E15,ListaMoedas,0),3),1)) | H15: =IF(F15="","",F15*G15)
G16: =IF(E16="","",IFERROR(INDEX(TaxaCambioTbl,MATCH(E16,ListaMoedas,0),3),1)) | H16: =IF(F16="","",F16*G16)
G17: =IF(E17="","",IFERROR(INDEX(TaxaCambioTbl,MATCH(E17,ListaMoedas,0),3),1)) | H17: =IF(F17="","",F17*G17)
G18: =IF(E18="","",IFERROR(INDEX(TaxaCambioTbl,MATCH(E18,ListaMoedas,0),3),1)) | H18: =IF(F18="","",F18*G18)
G19: =IF(E19="","",IFERROR(INDEX(TaxaCambioTbl,MATCH(E19,ListaMoedas,0),3),1)) | H19: =IF(F19="","",F19*G19)
G20: =IF(E20="","",IFERROR(INDEX(TaxaCambioTbl,MATCH(E20,ListaMoedas,0),3),1)) | H20: =IF(F20="","",F20*G20)
... G38: =IF(E38="","",IFERROR(INDEX(TaxaCambioTbl,MATCH(E38,ListaMoedas,0),3),1)) | H38: =IF(F38="","",F38*G38)
A39: TOTAL | H39: =SUM(H4:H38)

Sheet Compras
A1: LISTA DE COMPRAS DA VIAGEM
A2: Linhas 4-9 são EXEMPLOS. Marque "Sim" em Comprado assim que adquirir o item.
A3: Item | B3: Categoria | C3: Prioridade | D3: Preço Estimado (Moeda Local) | E3: Moeda | F3: Taxa de Câmbio | G3: Preço Estimado (Moeda Base) | H3: Comprado? | I3: Loja/Local | J3: Notas
A4: Vinho do Porto (garrafa) | B4: Alimentos e Bebidas | C4: Média | D4: 15 | E4: EUR | F4: =IF(E4="","",IFERROR(INDEX(TaxaCambioTbl,MATCH(E4,ListaMoedas,0),3),1)) | G4: =IF(D4="","",D4*F4) | H4: Não | I4: Adega em Porto
A5: Azulejos decorativos | B5: Presentes/Souvenirs | C5: Baixa | D5: 25 | E5: EUR | F5: =IF(E5="","",IFERROR(INDEX(TaxaCambioTbl,MATCH(E5,ListaMoedas,0),3),1)) | G5: =IF(D5="","",D5*F5) | H5: Não | I5: Feira da Ladra
A6: Tênis de couro português | B6: Roupas e Calçados | C6: Alta | D6: 90 | E6: EUR | F6: =IF(E6="","",IFERROR(INDEX(TaxaCambioTbl,MATCH(E6,ListaMoedas,0),3),1)) | G6: =IF(D6="","",D6*F6) | H6: Não | I6: Loja no Chiado
A7: Presente para família (3 un.) | B7: Presentes/Souvenirs | C7: Alta | D7: 60 | E7: EUR | F7: =IF(E7="","",IFERROR(INDEX(TaxaCambioTbl,MATCH(E7,ListaMoedas,0),3),1)) | G7: =IF(D7="","",D7*F7) | H7: Não | I7: A definir
A8: Pastéis de nata (caixa) | B8: Alimentos e Bebidas | C8: Baixa | D8: 12 | E8: EUR | F8: =IF(E8="","",IFERROR(INDEX(TaxaCambioTbl,MATCH(E8,ListaMoedas,0),3),1)) | G8: =IF(D8="","",D8*F8) | H8: Não | I8: Pastelaria
A9: Adaptador de tomada extra | B9: Eletrônicos | C9: Média | D9: 8 | E9: EUR | F9: =IF(E9="","",IFERROR(INDEX(TaxaCambioTbl,MATCH(E9,ListaMoedas,0),3),1)) | G9: =IF(D9="","",D9*F9) | H9: Sim | I9: Comprado no Brasil
F10: =IF(E10="","",IFERROR(INDEX(TaxaCambioTbl,MATCH(E10,ListaMoedas,0),3),1)) | G10: =IF(D10="","",D10*F10)
F11: =IF(E11="","",IFERROR(INDEX(TaxaCambioTbl,MATCH(E11,ListaMoedas,0),3),1)) | G11: =IF(D11="","",D11*F11)
F12: =IF(E12="","",IFERROR(INDEX(TaxaCambioTbl,MATCH(E12,ListaMoedas,0),3),1)) | G12: =IF(D12="","",D12*F12)
F13: =IF(E13="","",IFERROR(INDEX(TaxaCambioTbl,MATCH(E13,ListaMoedas,0),3),1)) | G13: =IF(D13="","",D13*F13)
F14: =IF(E14="","",IFERROR(INDEX(TaxaCambioTbl,MATCH(E14,ListaMoedas,0),3),1)) | G14: =IF(D14="","",D14*F14)
F15: =IF(E15="","",IFERROR(INDEX(TaxaCambioTbl,MATCH(E15,ListaMoedas,0),3),1)) | G15: =IF(D15="","",D15*F15)
F16: =IF(E16="","",IFERROR(INDEX(TaxaCambioTbl,MATCH(E16,ListaMoedas,0),3),1)) | G16: =IF(D16="","",D16*F16)
F17: =IF(E17="","",IFERROR(INDEX(TaxaCambioTbl,MATCH(E17,ListaMoedas,0),3),1)) | G17: =IF(D17="","",D17*F17)
F18: =IF(E18="","",IFERROR(INDEX(TaxaCambioTbl,MATCH(E18,ListaMoedas,0),3),1)) | G18: =IF(D18="","",D18*F18)
F19: =IF(E19="","",IFERROR(INDEX(TaxaCambioTbl,MATCH(E19,ListaMoedas,0),3),1)) | G19: =IF(D19="","",D19*F19)
F20: =IF(E20="","",IFERROR(INDEX(TaxaCambioTbl,MATCH(E20,ListaMoedas,0),3),1)) | G20: =IF(D20="","",D20*F20)
F21: =IF(E21="","",IFERROR(INDEX(TaxaCambioTbl,MATCH(E21,ListaMoedas,0),3),1)) | G21: =IF(D21="","",D21*F21)
... F24: =IF(E24="","",IFERROR(INDEX(TaxaCambioTbl,MATCH(E24,ListaMoedas,0),3),1)) | G24: =IF(D24="","",D24*F24)
A25: TOTAL ESTIMADO | G25: =SUM(G4:G24)
A27: Já comprado (Moeda Base): | B27: =SUMIF(H4:H24,"Sim",G4:G24)
A28: Falta comprar (Moeda Base): | B28: =SUMIF(H4:H24,"Não",G4:G24)

Sheet Historico
A1: HISTÓRICO DE VIAGENS
A2: Linhas 4-6 são EXEMPLOS de viagens passadas (valores já na moeda base). Some suas próprias viagens depois de cada retorno para criar seu histórico de gastos.
A3: Viagem | B3: Destino | C3: Data Início | D3: Data Fim | E3: Dias | F3: Nº Pessoas | G3: Moeda Local | H3: Orçamento (Moeda Base) | I3: Gasto Real (Moeda Base) | J3: Diferença | K3: % Usado | L3: Custo/Dia | M3: Custo/Pessoa/ Dia | N3: Nota (1-5) | O3: Notas
A4: Buenos Aires 2024 | B4: Buenos Aires, Argentina | C4: 45296 | D4: 45303 | E4: =IF(OR(C4="",D4=""),"",D4-C4+1) | F4: 2 | G4: ARS | H4: 4500 | I4: 4820 | J4: =IF(OR(H4="",I4=""),"",H4-I4) | K4: =IF(OR(H4="",H4=0),"",I4/H4) | L4: =IF(OR(I4="",E4="",E4=0),"",I4/E4) | M4: =IF(OR(L4="",F4="",F4=0),"",L4/F4) | N4: 4 | O4: Ótima viagem, câmbio favoreceu
A5: Nova York 2024 | B5: Nova York, EUA | C5: 45616 | D5: 45623 | E5: =IF(OR(C5="",D5=""),"",D5-C5+1) | F5: 1 | G5: USD | H5: 8000 | I5: 7650 | J5: =IF(OR(H5="",I5=""),"",H5-I5) | K5: =IF(OR(H5="",H5=0),"",I5/H5) | L5: =IF(OR(I5="",E5="",E5=0),"",I5/E5) | M5: =IF(OR(L5="",F5="",F5=0),"",L5/F5) | N5: 5 | O5: Ficou abaixo do orçamento
A6: Bariloche 2025 | B6: Bariloche, Argentina | C6: 45848 | D6: 45855 | E6: =IF(OR(C6="",D6=""),"",D6-C6+1) | F6: 2 | G6: ARS | H6: 6000 | I6: 6300 | J6: =IF(OR(H6="",I6=""),"",H6-I6) | K6: =IF(OR(H6="",H6=0),"",I6/H6) | L6: =IF(OR(I6="",E6="",E6=0),"",I6/E6) | M6: =IF(OR(L6="",F6="",F6=0),"",L6/F6) | N6: 4 | O6: Estourou um pouco em passeios
E7: =IF(OR(C7="",D7=""),"",D7-C7+1) | J7: =IF(OR(H7="",I7=""),"",H7-I7) | K7: =IF(OR(H7="",H7=0),"",I7/H7) | L7: =IF(OR(I7="",E7="",E7=0),"",I7/E7) | M7: =IF(OR(L7="",F7="",F7=0),"",L7/F7)
E8: =IF(OR(C8="",D8=""),"",D8-C8+1) | J8: =IF(OR(H8="",I8=""),"",H8-I8) | K8: =IF(OR(H8="",H8=0),"",I8/H8) | L8: =IF(OR(I8="",E8="",E8=0),"",I8/E8) | M8: =IF(OR(L8="",F8="",F8=0),"",L8/F8)
E9: =IF(OR(C9="",D9=""),"",D9-C9+1) | J9: =IF(OR(H9="",I9=""),"",H9-I9) | K9: =IF(OR(H9="",H9=0),"",I9/H9) | L9: =IF(OR(I9="",E9="",E9=0),"",I9/E9) | M9: =IF(OR(L9="",F9="",F9=0),"",L9/F9)
E10: =IF(OR(C10="",D10=""),"",D10-C10+1) | J10: =IF(OR(H10="",I10=""),"",H10-I10) | K10: =IF(OR(H10="",H10=0),"",I10/H10) | L10: =IF(OR(I10="",E10="",E10=0),"",I10/E10) | M10: =IF(OR(L10="",F10="",F10=0),"",L10/F10)
E11: =IF(OR(C11="",D11=""),"",D11-C11+1) | J11: =IF(OR(H11="",I11=""),"",H11-I11) | K11: =IF(OR(H11="",H11=0),"",I11/H11) | L11: =IF(OR(I11="",E11="",E11=0),"",I11/E11) | M11: =IF(OR(L11="",F11="",F11=0),"",L11/F11)
E12: =IF(OR(C12="",D12=""),"",D12-C12+1) | J12: =IF(OR(H12="",I12=""),"",H12-I12) | K12: =IF(OR(H12="",H12=0),"",I12/H12) | L12: =IF(OR(I12="",E12="",E12=0),"",I12/E12) | M12: =IF(OR(L12="",F12="",F12=0),"",L12/F12)
E13: =IF(OR(C13="",D13=""),"",D13-C13+1) | J13: =IF(OR(H13="",I13=""),"",H13-I13) | K13: =IF(OR(H13="",H13=0),"",I13/H13) | L13: =IF(OR(I13="",E13="",E13=0),"",I13/E13) | M13: =IF(OR(L13="",F13="",F13=0),"",L13/F13)
E14: =IF(OR(C14="",D14=""),"",D14-C14+1) | J14: =IF(OR(H14="",I14=""),"",H14-I14) | K14: =IF(OR(H14="",H14=0),"",I14/H14) | L14: =IF(OR(I14="",E14="",E14=0),"",I14/E14) | M14: =IF(OR(L14="",F14="",F14=0),"",L14/F14)
E15: =IF(OR(C15="",D15=""),"",D15-C15+1) | J15: =IF(OR(H15="",I15=""),"",H15-I15) | K15: =IF(OR(H15="",H15=0),"",I15/H15) | L15: =IF(OR(I15="",E15="",E15=0),"",I15/E15) | M15: =IF(OR(L15="",F15="",F15=0),"",L15/F15)
E16: =IF(OR(C16="",D16=""),"",D16-C16+1) | J16: =IF(OR(H16="",I16=""),"",H16-I16) | K16: =IF(OR(H16="",H16=0),"",I16/H16) | L16: =IF(OR(I16="",E16="",E16=0),"",I16/E16) | M16: =IF(OR(L16="",F16="",F16=0),"",L16/F16)
E17: =IF(OR(C17="",D17=""),"",D17-C17+1) | J17: =IF(OR(H17="",I17=""),"",H17-I17) | K17: =IF(OR(H17="",H17=0),"",I17/H17) | L17: =IF(OR(I17="",E17="",E17=0),"",I17/E17) | M17: =IF(OR(L17="",F17="",F17=0),"",L17/F17)
E18: =IF(OR(C18="",D18=""),"",D18-C18+1) | J18: =IF(OR(H18="",I18=""),"",H18-I18) | K18: =IF(OR(H18="",H18=0),"",I18/H18) | L18: =IF(OR(I18="",E18="",E18=0),"",I18/E18) | M18: =IF(OR(L18="",F18="",F18=0),"",L18/F18)
... E33: =IF(OR(C33="",D33=""),"",D33-C33+1) | J33: =IF(OR(H33="",I33=""),"",H33-I33) | K33: =IF(OR(H33="",H33=0),"",I33/H33) | L33: =IF(OR(I33="",E33="",E33=0),"",I33/E33) | M33: =IF(OR(L33="",F33="",F33=0),"",L33/F33)
A35: MÉDIA HISTÓRICA | L35: =IFERROR(AVERAGE(L4:L33),"") | M35: =IFERROR(AVERAGE(M4:M33),"")
